<root><separator>kterou</separator><separator>zda</separator><separator>z</separator><separator>či</separator><separator>jestliže</separator><separator>takže</separator><separator>avšak</separator><separator>ovšem</separator><separator>že</separator><separator>čím</separator><separator>kteří</separator><separator>kde</separator><separator>však</separator><separator>kdežto</separator><separator>:</separator><separator>(</separator><separator>jakýsi</separator><separator>neboť</separator><separator>jež</separator><separator>před</separator><separator>jestli</separator><separator>?</separator><separator>kudy</separator><separator>protože</separator><separator>pokud</separator><separator>kdy</separator><separator>ve</separator><separator>jako</separator><separator>nichž</separator><separator>nebo</separator><separator>kterými</separator><separator>ale</separator><separator>když</separator><separator>jakož</separator><separator>kterým</separator><separator>,</separator><separator>přičemž</separator><separator>jenže</separator><separator>buď</separator><separator>-</separator><separator>byť</separator><separator>jednak</separator><separator>jací</separator><separator>i</separator><separator>buďto</separator><separator>aniž</separator><separator>)</separator><separator>tudíž</separator><separator>jaké</separator><separator>jakoby</separator><separator>které</separator><separator>která</separator><separator>kam</separator><separator>proto</separator><separator>mezi</separator><separator>a</separator><separator>aby</separator><separator>vždyť</separator><separator>!</separator><separator>ani</separator><separator>u</separator><separator>do</separator><separator>až</separator><separator>tj</separator><separator>nímž</separator><separator>kdo</separator><separator>co</separator><separator>.</separator><separator>jehož</separator><separator>než</separator><separator>kterému</separator><separator>který</separator><separator>jakými</separator><separator>ač</separator><separator>proč</separator><separator>jak</separator><separator>zatímco</separator><separator>čímž</separator><separator>leč</separator><separator>což</separator></root>